pysine/__init__.py
pysine/__main__.py
pysine/_version.py
pysine/pysine.py
pysine-0.9.2.dist-info/DESCRIPTION.rst
pysine-0.9.2.dist-info/METADATA
pysine-0.9.2.dist-info/RECORD
pysine-0.9.2.dist-info/WHEEL
pysine-0.9.2.dist-info/metadata.json
pysine-0.9.2.dist-info/top_level.txt
