Metadata-Version: 1.1
Name: pysine
Version: 0.9.2
Summary: Allows to play single tones on the PyAudio sound output in real time
Home-page: http://www.github.com/lneuhaus/pysine
Author: Leonhard Neuhaus
Author-email: leonhard.neuhaus@gmail.com
License: GPLv3
Keywords: sound PyAudio sine wave output play
Platform: any
Classifier: Programming Language :: Python :: 2.7
Classifier: Programming Language :: Python :: 3.4
Classifier: Programming Language :: Python :: 3.5
Classifier: Programming Language :: Python :: 3.6
Classifier: Natural Language :: English
Classifier: Development Status :: 4 - Beta
Classifier: License :: OSI Approved :: GNU General Public License v3 (GPLv3)
Classifier: Topic :: Scientific/Engineering :: Human Machine Interfaces
